tests/__init__.py
tests/test_hash.py
tests/test_json.py
tests/test_yaml.py
wozoxutils/__init__.py
wozoxutils/file.py
wozoxutils/hash.py
wozoxutils/json.py
wozoxutils/yaml.py
wozoxutils-0.2.6.dist-info/LICENSE
wozoxutils-0.2.6.dist-info/METADATA
wozoxutils-0.2.6.dist-info/WHEEL
wozoxutils-0.2.6.dist-info/top_level.txt
wozoxutils-0.2.6.dist-info/RECORD
