Metadata-Version: 2.1
Name: wozoxutils
Version: 0.2.6
Summary: general-purpose library for Python that contains various commonly used functional modules
Home-page: https://github.com/wozox/wozoxutils-py
Author: illiten
Author-email: admin@leelib.com
Keywords: wozox utils
Classifier: License :: OSI Approved :: MIT License
Classifier: Programming Language :: Python
Classifier: Programming Language :: Python :: 3
Classifier: Topic :: Software Development :: Libraries :: Python Modules
License-File: LICENSE
Requires-Dist: pyyaml (>=6.0)
